tfrecommender
