Metadata-Version: 1.0
Name: tfrecommender
Version: 0.1.1.dev3
Summary: recommender systems using TensorFlow and embeddings
Home-page: https://github.com/subarnab219/tfrecommender.git
Author: Subarna Rana, Abhishek Kumar
Author-email: subarna.rana2@gmail.com
License: MIT
Platform: UNKNOWN
